LICENSE
setup.py
ReneTkinter.egg-info/PKG-INFO
ReneTkinter.egg-info/SOURCES.txt
ReneTkinter.egg-info/dependency_links.txt
ReneTkinter.egg-info/requires.txt
ReneTkinter.egg-info/top_level.txt
Tkinters/VisualPython.py
Tkinters/VisualPythonBasicos.py
Tkinters/__init__.py
Tkinters/ClasesUtiles/ConjuntoGrid.py
Tkinters/ClasesUtiles/CoordenadaGrid.py
Tkinters/ClasesUtiles/__init__.py
Tkinters/ClasesUtiles/Componentes/AreaDeTexto.py
Tkinters/ClasesUtiles/Componentes/Boton.py
Tkinters/ClasesUtiles/Componentes/CheckBox.py
Tkinters/ClasesUtiles/Componentes/CuadroDeTexto.py
Tkinters/ClasesUtiles/Componentes/FrameVentana.py
Tkinters/ClasesUtiles/Componentes/Labelr.py
Tkinters/ClasesUtiles/Componentes/ListBox.py
Tkinters/ClasesUtiles/Componentes/Menur.py
Tkinters/ClasesUtiles/Componentes/RadioButton.py
Tkinters/ClasesUtiles/Componentes/Ventana.py
Tkinters/ClasesUtiles/Componentes/__init__.py
Tkinters/ClasesUtiles/Interfaces/Componente.py
Tkinters/ClasesUtiles/Interfaces/ComponenteConAction.py
Tkinters/ClasesUtiles/Interfaces/ComponenteConText.py
Tkinters/ClasesUtiles/Interfaces/__init__.py
Tkinters/ClasesUtiles/Tipos/TipoDeAnclaje.py
Tkinters/ClasesUtiles/Tipos/TipoDeBorde.py
Tkinters/ClasesUtiles/Tipos/TipoDeCursor.py
Tkinters/ClasesUtiles/Tipos/TipoDeJustificacion.py
Tkinters/ClasesUtiles/Tipos/__init__.py
Tkinters/Imports/VisualPythonBasicosImports.py
Tkinters/Imports/__init__.py